Metadata-Version: 1.1
Name: datacli
Version: 0.1.3
Summary: Productive no-sql data sources exploration with SQL, Pandas and shortcuts
Home-page: https://github.com/hackliff/datacli
Author: hackliff
Author-email: xavier.bruhiere@gmail.com
License: UNKNOWN
Keywords: data,database,analysis,cli,tool
Platform: UNKNOWN
Classifier: Intended Audience :: Developers
Classifier: License :: OSI Approved :: MIT License
Classifier: Operating System :: Unix
Classifier: Programming Language :: Python
Classifier: Programming Language :: Python :: 2.7
Classifier: Programming Language :: Python :: 3
Classifier: Programming Language :: Python :: 3.4
Classifier: Programming Language :: SQL
Classifier: Topic :: Database
Classifier: Topic :: Database :: Front-Ends
Classifier: Topic :: Software Development
Classifier: Topic :: Software Development :: Libraries :: Python Modules
